bls_datasets/__init__.py
bls_datasets/oes.py
bls_datasets/qcew.py
bls_datasets/util.py
bls_datasets-0.0.9.dist-info/LICENSE
bls_datasets-0.0.9.dist-info/METADATA
bls_datasets-0.0.9.dist-info/WHEEL
bls_datasets-0.0.9.dist-info/top_level.txt
bls_datasets-0.0.9.dist-info/RECORD
