Metadata-Version: 2.1
Name: bls-datasets
Version: 0.0.9
Summary: Python library for retrieving BLS datasets
Home-page: https://github.com/mbkupfer/bls-datasets
Author: Maxim Kupfer
Author-email: mbkupfer@gmail.com
License: UNKNOWN
Platform: UNKNOWN
Classifier: Development Status :: 4 - Beta
Classifier: Intended Audience :: Developers
Classifier: Intended Audience :: Education
Classifier: Intended Audience :: Financial and Insurance Industry
Classifier: Intended Audience :: Science/Research
Classifier: Programming Language :: Python :: 3.6
Classifier: Programming Language :: Python :: 3.7
Classifier: License :: OSI Approved :: MIT License
Classifier: Operating System :: OS Independent
Classifier: Topic :: Office/Business
Classifier: Topic :: Office/Business :: Financial
Classifier: Topic :: Scientific/Engineering
Requires-Dist: pandas (>=0.23.4)
Requires-Dist: xlrd (>=1.1.0)
Requires-Dist: requests (>=2.19.1)
